{"type": "Feature", "id": 12513335, "geometry": {"type": "Point", "coordinates": [-89.848602, 15.8056]}, "properties": {"woe:id": 12513335, "woe:parent_id": 82103, "woe:name": "Inta Northeast Airport", "woe:placetype": 14, "woe:placetype_name": "Airport", "woe:lang": "ENG", "iso:country": "GT", "meta:provider": ["geoplanet:7.3.1", "geoplanet:7.3.2", "geoplanet:7.4.0", "geoplanet:7.4.1", "geoplanet:7.5.1", "geoplanet:7.5.2", "geoplanet:7.6.0", "geoplanet:7.8.1", "geoplanet:7.9.0", "geoplanet:7.10.0", "geoplanet:8.0.0", "woeplanet:8.0.0"], "meta:indexed": "2020-08-20T21:02:13.979370", "meta:updated": "2020-10-14T11:19:25.370685", "woe:hierarchy": {"continent": 24865672, "country": 23424834, "town": 0, "planet": 1, "county": 26806910, "suburb": 0, "state": 2345552, "region": 0, "localadmin": 0}, "woe:timezone_id": 28350761, "woe:hash": "d4b1gmq4rc6s", "woe:centroid": [-89.848602, 15.8056], "geom:latitude": 15.8056, "geom:longitude": -89.848602, "geom:hash": "d4b1gmq4rc6s", "woe:latitude": 15.8056, "geom:centroid": [-89.848602, 15.8056], "woe:longitude": -89.848602, "woe:repo": "woeplanet-airport-gt", "geom:area": 0.0, "woe:scale": 19}}